Workbook

Sheet merge
A1: Year | B1: Country | C1: Number | D1: Indicator | E1: Value
A2: 2021 | B2: Brazil | C2: 58059 | D2: Cereal yield (kg per hectare) | E2: 4477.4
A3: 2021 | B3: Brazil | C3: 58059 | D3: Inflation, consumer prices (annual %) | E3: 8.30165975585673
A4: 2021 | B4: Brazil | C4: 58059 | D4: Deposit interest rate (%) | E4: 4.3480539
A5: 2021 | B5: Brazil | C5: 58059 | D5: Lending interest rate (%) | E5: 30.0166666666667
A6: 2021 | B6: Brazil | C6: 58059 | D6: Central government debt, total (% of GDP) | E6: 85.0115036701985
A7: 2021 | B7: Brazil | C7: 58059 | D7: Military expenditure (% of GDP) | E7: 1.16368211072875
A8: 2021 | B8: Brazil | C8: 58059 | D8: GDP (current US$) | E8: 1670647399034.67
A9: 2021 | B9: Brazil | C9: 58059 | D9: Poverty headcount ratio at $2.15 a day (2017 PPP) (% of population) | E9: 5.8
A10: 2021 | B10: Brazil | C10: 58059 | D10: Labor force, total | E10: 106047171
A11: 2021 | B11: Brazil | C11: 58059 | D11: Unemployment, total (% of total labor force) (modeled ILO estimate) | E11: 13.159
A12: 2021 | B12: Brazil | C12: 58059 | D12: Birth rate, crude (per 1,000 people) | E12: 12.883
A13: 2021 | B13: Brazil | C13: 58059 | D13: High-technology exports (current US$) | E13: 6350114829
A14: 2021 | B14: Brazil | C14: 58059 | D14: GDP growth (annual %) | E14: 4.76260437908608
A15: 2021 | B15: Brazil | C15: 58059 | D15: people_sum | E15: 214326223
A16: 2021 | B16: Brazil | C16: 58059 | D16: Death rate, crude (per 1,000 people) | E16: 8.326
A17: 2021 | B17: Canada | C17: 22371 | D17: Cereal yield (kg per hectare) | E17: 3120
A18: 2021 | B18: Canada | C18: 22371 | D18: Inflation, consumer prices (annual %) | E18: 3.39519318527528
A19: 2021 | B19: Canada | C19: 22371 | D19: Research and development expenditure (% of GDP) | E19: 1.69727003574371
A20: 2021 | B20: Canada | C20: 22371 | D20: Central government debt, total (% of GDP) | E20: 71.0739602315819
A21: 2021 | B21: Canada | C21: 22371 | D21: Military expenditure (% of GDP) | E21: 1.26729446473527
A22: 2021 | B22: Canada | C22: 22371 | D22: GDP (current US$) | E22: 2007472181464.15
A23: 2021 | B23: Canada | C23: 22371 | D23: Government expenditure on education, total (% of GDP) | E23: 4.59400606155396
A24: 2021 | B24: Canada | C24: 22371 | D24: Labor force, total | E24: 20967796
A25: 2021 | B25: Canada | C25: 22371 | D25: Unemployment, total (% of total labor force) (modeled ILO estimate) | E25: 7.527
A26: 2021 | B26: Canada | C26: 22371 | D26: Birth rate, crude (per 1,000 people) | E26: 9.7
A27: 2021 | B27: Canada | C27: 22371 | D27: High-technology exports (current US$) | E27: 29239719472
A28: 2021 | B28: Canada | C28: 22371 | D28: GDP growth (annual %) | E28: 5.28695689105889
A29: 2021 | B29: Canada | C29: 22371 | D29: people_sum | E29: 38239864
A30: 2021 | B30: Canada | C30: 22371 | D30: Death rate, crude (per 1,000 people) | E30: 8.2
A31: 2021 | B31: China | C31: 23471 | D31: Cereal yield (kg per hectare) | E31: 6316.7
A32: 2021 | B32: China | C32: 23471 | D32: Inflation, consumer prices (annual %) | E32: 0.981015135544882
A33: 2021 | B33: China | C33: 23471 | D33: Deposit interest rate (%) | E33: 1.5
A34: 2021 | B34: China | C34: 23471 | D34: Lending interest rate (%) | E34: 4.35
A35: 2021 | B35: China | C35: 23471 | D35: Research and development expenditure (% of GDP) | E35: 2.4326000213623
A36: 2021 | B36: China | C36: 23471 | D36: Military expenditure (% of GDP) | E36: 1.61307386433133
A37: 2021 | B37: China | C37: 23471 | D37: GDP (current US$) | E37: 17820459508852.2
A38: 2021 | B38: China | C38: 23471 | D38: Government expenditure on education, total (% of GDP) | E38: 3.29784345626831
A39: 2021 | B39: China | C39: 23471 | D39: Labor force, total | E39: 780370660
A40: 2021 | B40: China | C40: 23471 | D40: Unemployment, total (% of total labor force) (modeled ILO estimate) | E40: 4.55
A41: 2021 | B41: China | C41: 23471 | D41: Birth rate, crude (per 1,000 people) | E41: 7.52
A42: 2021 | B42: China | C42: 23471 | D42: Researchers in R&D (per million people) | E42: 1687.05676269531
A43: 2021 | B43: China | C43: 23471 | D43: High-technology exports (current US$) | E43: 942314815525
A44: 2021 | B44: China | C44: 23471 | D44: GDP growth (annual %) | E44: 8.44846941687277
A45: 2021 | B45: China | C45: 23471 | D45: people_sum | E45: 1412360000
A46: 2021 | B46: China | C46: 23471 | D46: Death rate, crude (per 1,000 people) | E46: 7.18
A47: 2021 | B47: Colombia | C47: 10495 | D47: Cereal yield (kg per hectare) | E47: 4280.2
A48: 2021 | B48: Colombia | C48: 10495 | D48: Inflation, consumer prices (annual %) | E48: 3.49505757399448
A49: 2021 | B49: Colombia | C49: 10495 | D49: Deposit interest rate (%) | E49: 2.07264966142457
A50: 2021 | B50: Colombia | C50: 10495 | D50: Lending interest rate (%) | E50: 9.3378484091001
A51: 2021 | B51: Colombia | C51: 10495 | D51: Central government debt, total (% of GDP) | E51: 80.3666516174088
A52: 2021 | B52: Colombia | C52: 10495 | D52: Military expenditure (% of GDP) | E52: 3.23758910406394
A53: 2021 | B53: Colombia | C53: 10495 | D53: GDP (current US$) | E53: 318524633225.395
A54: 2021 | B54: Colombia | C54: 10495 | D54: Government expenditure on education, total (% of GDP) | E54: 3.92000007629395
A55: 2021 | B55: Colombia | C55: 10495 | D55: Poverty headcount ratio at $2.15 a day (2017 PPP) (% of population) | E55: 7.3
A56: 2021 | B56: Colombia | C56: 10495 | D56: Labor force, total | E56: 25983568
A57: 2021 | B57: Colombia | C57: 10495 | D57: Unemployment, total (% of total labor force) (modeled ILO estimate) | E57: 13.898
A58: 2021 | B58: Colombia | C58: 10495 | D58: Birth rate, crude (per 1,000 people) | E58: 14.204
A59: 2021 | B59: Colombia | C59: 10495 | D59: High-technology exports (current US$) | E59: 735048087
A60: 2021 | B60: Colombia | C60: 10495 | D60: GDP growth (annual %) | E60: 10.8011981904878
A61: 2021 | B61: Colombia | C61: 10495 | D61: people_sum | E61: 51516562
A62: 2021 | B62: Colombia | C62: 10495 | D62: Death rate, crude (per 1,000 people) | E62: 7.735
A63: 2021 | B63: Cuba | C63: 39303 | D63: Cereal yield (kg per hectare) | E63: 2406.1
A64: 2021 | B64: Cuba | C64: 39303 | D64: Research and development expenditure (% of GDP) | E64: 0.322820007801056
A65: 2021 | B65: Cuba | C65: 39303 | D65: Literacy rate, adult total (% of people ages 15 and above) | E65: 99.6731109619141
A66: 2021 | B66: Cuba | C66: 39303 | D66: Government expenditure on education, total (% of GDP) | E66: 9.38599967956543
A67: 2021 | B67: Cuba | C67: 39303 | D67: Labor force, total | E67: 5106046
A68: 2021 | B68: Cuba | C68: 39303 | D68: Unemployment, total (% of total labor force) (modeled ILO estimate) | E68: 1.373
A69: 2021 | B69: Cuba | C69: 39303 | D69: Birth rate, crude (per 1,000 people) | E69: 8.922
A70: 2021 | B70: Cuba | C70: 39303 | D70: GDP growth (annual %) | E70: 1.25369342501311
A71: 2021 | B71: Cuba | C71: 39303 | D71: people_sum | E71: 11256372
A72: 2021 | B72: Cuba | C72: 39303 | D72: Death rate, crude (per 1,000 people) | E72: 14.652
A73: 2021 | B73: Ecuador | C73: 97074 | D73: Cereal yield (kg per hectare) | E73: 4015
A74: 2021 | B74: Ecuador | C74: 97074 | D74: Inflation, consumer prices (annual %) | E74: 0.133251386096389
A75: 2021 | B75: Ecuador | C75: 97074 | D75: Deposit interest rate (%) | E75: 4.1625
A76: 2021 | B76: Ecuador | C76: 97074 | D76: Military expenditure (% of GDP) | E76: 2.24439369241334
A77: 2021 | B77: Ecuador | C77: 97074 | D77: GDP (current US$) | E77: 107435101000
A78: 2021 | B78: Ecuador | C78: 97074 | D78: Literacy rate, adult total (% of people ages 15 and above) | E78: 94.4835891723633
A79: 2021 | B79: Ecuador | C79: 97074 | D79: Government expenditure on education, total (% of GDP) | E79: 3.6913800239563
A80: 2021 | B80: Ecuador | C80: 97074 | D80: Poverty headcount ratio at $2.15 a day (2017 PPP) (% of population) | E80: 3.6
A81: 2021 | B81: Ecuador | C81: 97074 | D81: Labor force, total | E81: 8652009
A82: 2021 | B82: Ecuador | C82: 97074 | D82: Unemployment, total (% of total labor force) (modeled ILO estimate) | E82: 4.552
A83: 2021 | B83: Ecuador | C83: 97074 | D83: Birth rate, crude (per 1,000 people) | E83: 16.817
A84: 2021 | B84: Ecuador | C84: 97074 | D84: High-technology exports (current US$) | E84: 77485368
A85: 2021 | B85: Ecuador | C85: 97074 | D85: GDP growth (annual %) | E85: 9.8184177
A86: 2021 | B86: Ecuador | C86: 97074 | D86: people_sum | E86: 17797737
A87: 2021 | B87: Ecuador | C87: 97074 | D87: Death rate, crude (per 1,000 people) | E87: 6.719
A88: 2021 | B88: El Salvador | C88: 99463 | D88: Cereal yield (kg per hectare) | E88: 2950.3
A89: 2021 | B89: El Salvador | C89: 99463 | D89: Inflation, consumer prices (annual %) | E89: 3.46692585313082
A90: 2021 | B90: El Salvador | C90: 99463 | D90: Research and development expenditure (% of GDP) | E90: 0.160260006785393
A91: 2021 | B91: El Salvador | C91: 99463 | D91: Central government debt, total (% of GDP) | E91: 66.4690525886664
A92: 2021 | B92: El Salvador | C92: 99463 | D92: Military expenditure (% of GDP) | E92: 1.22343572258204
A93: 2021 | B93: El Salvador | C93: 99463 | D93: GDP (current US$) | E93: 29043140000
A94: 2021 | B94: El Salvador | C94: 99463 | D94: Government expenditure on education, total (% of GDP) | E94: 3.52807998657227
A95: 2021 | B95: El Salvador | C95: 99463 | D95: Poverty headcount ratio at $2.15 a day (2017 PPP) (% of population) | E95: 3.6
A96: 2021 | B96: El Salvador | C96: 99463 | D96: Labor force, total | E96: 2768977
A97: 2021 | B97: El Salvador | C97: 99463 | D97: Unemployment, total (% of total labor force) (modeled ILO estimate) | E97: 4.327
A98: 2021 | B98: El Salvador | C98: 99463 | D98: Birth rate, crude (per 1,000 people) | E98: 16.025
A99: 2021 | B99: El Salvador | C99: 99463 | D99: Researchers in R&D (per million people) | E99: 64.7152709960938
A100: 2021 | B100: El Salvador | C100: 99463 | D100: High-technology exports (current US$) | E100: 348603292
...

Sheet Sheet1
A1: Number | B1: Value | C1: Number(秩) | D1: Value(秩)
A2: 58059 | B2: 12.883 | C2: =VLOOKUP(A2,Sheet3!A:B,2,0) -> 27 | D2: =VLOOKUP(B2,Sheet2!A:B,2,0) -> 14
A3: 22371 | B3: 9.7 | C3: =VLOOKUP(A3,Sheet3!A:B,2,0) -> 11 | D3: =VLOOKUP(B3,Sheet2!A:B,2,0) -> 11
A4: 23471 | B4: 7.52 | C4: =VLOOKUP(A4,Sheet3!A:B,2,0) -> 12 | D4: =VLOOKUP(B4,Sheet2!A:B,2,0) -> 3
A5: 10495 | B5: 14.204 | C5: =VLOOKUP(A5,Sheet3!A:B,2,0) -> 8 | D5: =VLOOKUP(B5,Sheet2!A:B,2,0) -> 16
A6: 39303 | B6: 8.922 | C6: =VLOOKUP(A6,Sheet3!A:B,2,0) -> 17 | D6: =VLOOKUP(B6,Sheet2!A:B,2,0) -> 7
A7: 97074 | B7: 16.817 | C7: =VLOOKUP(A7,Sheet3!A:B,2,0) -> 29 | D7: =VLOOKUP(B7,Sheet2!A:B,2,0) -> 28
A8: 99463 | B8: 16.025 | C8: =VLOOKUP(A8,Sheet3!A:B,2,0) -> 32 | D8: =VLOOKUP(B8,Sheet2!A:B,2,0) -> 24
A9: 284291 | B9: 21.12 | C9: =VLOOKUP(A9,Sheet3!A:B,2,0) -> 39 | D9: =VLOOKUP(B9,Sheet2!A:B,2,0) -> 38
A10: 48727 | B10: 23.498 | C10: =VLOOKUP(A10,Sheet3!A:B,2,0) -> 20 | D10: =VLOOKUP(B10,Sheet2!A:B,2,0) -> 42
A11: 321149 | B11: 21.071 | C11: =VLOOKUP(A11,Sheet3!A:B,2,0) -> 40 | D11: =VLOOKUP(B11,Sheet2!A:B,2,0) -> 37
A12: 30662 | B12: 16.419 | C12: =VLOOKUP(A12,Sheet3!A:B,2,0) -> 15 | D12: =VLOOKUP(B12,Sheet2!A:B,2,0) -> 26
A13: 674739 | B13: 14.857 | C13: =VLOOKUP(A13,Sheet3!A:B,2,0) -> 41 | D13: =VLOOKUP(B13,Sheet2!A:B,2,0) -> 20
... A43: 189520 | B43: 15.573 | C43: =VLOOKUP(A43,Sheet3!A:B,2,0) -> 35 | D43: =VLOOKUP(B43,Sheet2!A:B,2,0) -> 21
C44: 21.5 | D44: 21.47619

Sheet Sheet2
A1: Value
A2: 6.77 | B2: 1
A3: 7.3 | B3: 2
A4: 7.52 | B4: 3
A5: 7.659 | B5: 4
A6: 8.889 | B6: 5
A7: 8.9 | B7: 6
A8: 8.922 | B8: 7
A9: 9 | B9: 8
A10: 9.6 | B10: 9
A11: 9.6 | B11: 10
A12: 9.7 | B12: 11
A13: 10.1 | B13: 12
... A43: 23.498 | B43: 42

Sheet Sheet3
A1: 3841 | B1: 1
A2: 4470 | B2: 2
A3: 4989 | B3: 3
A4: 5159 | B4: 4
A5: 5177 | B5: 5
A6: 7411 | B6: 6
A7: 9378 | B7: 7
A8: 10495 | B8: 8
A9: 13240 | B9: 9
A10: 19470 | B10: 10
A11: 22371 | B11: 11
A12: 23471 | B12: 12
... A42: 823057 | B42: 42
